bumbo/__init__.py
bumbo/api.py
bumbo/middleware.py
bumbo/orm.py
bumbo/response.py
bumbo_ivan-0.0.8.dist-info/METADATA
bumbo_ivan-0.0.8.dist-info/WHEEL
bumbo_ivan-0.0.8.dist-info/top_level.txt
bumbo_ivan-0.0.8.dist-info/RECORD
