Metadata-Version: 2.1
Name: bumbo-ivan
Version: 0.0.8
Summary: Bumbo Python Web Framework build for learning purpose.
Home-page: UNKNOWN
Author: Ivan Domenech
Author-email: ivan.domenech.g@gmail.com
License: MIT
Platform: UNKNOWN
Classifier: Programming Language :: Python :: 3.6
Requires-Python: >=3.6.0
Requires-Dist: Jinja2 (==2.10.3)
Requires-Dist: WebOb (==1.8.5)
Requires-Dist: parse (==1.12.1)
Requires-Dist: requests-wsgi-adapter (==0.4.1)
Requires-Dist: requests (==2.22.0)
Requires-Dist: whitenoise (==4.1.4)
